{
    "civils": [
        {
            "Name": "Settlers",
            "Description": "Construct settlements from scratch",
            "EntityId": 0,
            "IconPath": "Sprites/settlers",
            "Health": 2,
            "MaxMovePoints": 2,
            "MaxActionPoints": 1,
            "Actions": [
                {
                    "FunctionName": "Settle",
                    "Description": "Settle here",
                    "ActionPoints": 1
                }
            ],
            "Cost": 5,
            "researchRequirement": -1

        }
    ]
}
